line_intersect_2d/__bootstrap__.cpython-38-x86_64-linux-gnu.so
line_intersect_2d/__init__.py
line_intersect_2d-1.2.3.dist-info/METADATA
line_intersect_2d-1.2.3.dist-info/WHEEL
line_intersect_2d-1.2.3.dist-info/top_level.txt
line_intersect_2d-1.2.3.dist-info/LICENSE
line_intersect_2d-1.2.3.dist-info/RECORD
