Metadata-Version: 2.1
Name: line-intersect-2d
Version: 1.2.3
Summary: Quadtree library for determining if 2D paths intersect
Home-page: https://github.com/cervi-robotics/line-intersect-2d
Author: Piotr Maślanka
Author-email: piotr.maslanka@henrietta.com.pl
License: UNKNOWN
Project-URL: Documentation, https://line-intersect-2d.readthedocs.io/
Project-URL: Code, https://github.com/cervi-robotics/line-intersect-2d
Project-URL: Issue tracker, https://github.com/cervi-robotics/line-intersect-2d/issues
Platform: UNKNOWN
Classifier: Programming Language :: Python
Classifier: Programming Language :: Python :: 3.5
Classifier: Programming Language :: Python :: 3.6
Classifier: Programming Language :: Python :: 3.7
Classifier: Programming Language :: Python :: 3.8
Classifier: Programming Language :: Python :: 3.9
Classifier: Programming Language :: Python :: Implementation :: CPython
Classifier: Operating System :: POSIX
Classifier: Operating System :: OS Independent
Classifier: Development Status :: 5 - Production/Stable
Classifier: License :: OSI Approved :: MIT License
Classifier: Topic :: Software Development :: Libraries
Requires-Python: !=2.7.*,!=3.0.*,!=3.1.*,!=3.2.*,!=3.3.*,!=3.4.*
Requires-Dist: satella
